chainsmith/__init__.py
chainsmith/commandline.py
chainsmith/config.py
chainsmith/config_file.py
chainsmith/exceptions.py
chainsmith/tls.py
chainsmith-0.2.5.dist-info/LICENSE
chainsmith-0.2.5.dist-info/METADATA
chainsmith-0.2.5.dist-info/WHEEL
chainsmith-0.2.5.dist-info/entry_points.txt
chainsmith-0.2.5.dist-info/top_level.txt
chainsmith-0.2.5.dist-info/RECORD
