Metadata-Version: 2.1
Name: chainsmith
Version: 0.2.5
Summary: A tool for easy creation of certificate chains
Home-page: https://github.com/MannemSolutions/ChainSmith
Author: Sebastiaan Mannem
Author-email: sebas@mannemsolutions.nl
License: GPL-3.0 License
Platform: UNKNOWN
Classifier: License :: OSI Approved :: GNU General Public License v3 (GPLv3)
Classifier: Programming Language :: Python :: 3
Classifier: Programming Language :: Python :: 3.8
Classifier: Programming Language :: Python :: 3.9
Classifier: Programming Language :: Python :: 3.10
Requires-Dist: PyYAML (==6.0)
